MANIFEST.in
README.md
license.txt
setup.py
RTM.egg-info/PKG-INFO
RTM.egg-info/SOURCES.txt
RTM.egg-info/dependency_links.txt
RTM.egg-info/top_level.txt
bin/sbdart/Makefile
bin/sbdart/Makefile~
bin/sbdart/atms.f
bin/sbdart/disort.f
bin/sbdart/disutil.f
bin/sbdart/drt.f
bin/sbdart/params.f
bin/sbdart/spectra.f
bin/sbdart/tauaero.f
bin/sbdart/tauaero.f~
bin/sbdart/taucloud.f
bin/sbdart/taugas.f
bin/smarts/Makefile
bin/smarts/Makefile~
bin/smarts/smarts295.f
bin/smarts/smarts295.f~
rtm/__init__.py
rtm/_rtm.py
rtm/sbdart.py
rtm/settings.py
rtm/smarts.py
rtm/data/smarts/Albedo/.DS_Store
rtm/data/smarts/Albedo/ALBEDO.DAT
rtm/data/smarts/Albedo/ALFALFA.DAT
rtm/data/smarts/Albedo/Asphalt.dat
rtm/data/smarts/Albedo/BASALT.DAT
rtm/data/smarts/Albedo/Birch.dat
rtm/data/smarts/Albedo/BlckLoam.dat
rtm/data/smarts/Albedo/BrwnLoam.dat
rtm/data/smarts/Albedo/BrwnSand.dat
rtm/data/smarts/Albedo/CONCRETE.DAT
rtm/data/smarts/Albedo/CSeaWatr.dat
rtm/data/smarts/Albedo/Conifers.dat
rtm/data/smarts/Albedo/DRY_SAND.DAT
rtm/data/smarts/Albedo/DarkLoam.dat
rtm/data/smarts/Albedo/DarkSand.dat
rtm/data/smarts/Albedo/Decidous.dat
rtm/data/smarts/Albedo/DryGrass.dat
rtm/data/smarts/Albedo/Dry_Soil.dat
rtm/data/smarts/Albedo/Dry_clay.dat
rtm/data/smarts/Albedo/DuneSand.dat
rtm/data/smarts/Albedo/Fallow.dat
rtm/data/smarts/Albedo/FibrGlss.dat
rtm/data/smarts/Albedo/FineSnow.dat
rtm/data/smarts/Albedo/FirTrees.dat
rtm/data/smarts/Albedo/GRASS.DAT
rtm/data/smarts/Albedo/Gravel.dat
rtm/data/smarts/Albedo/GrazingField.dat
rtm/data/smarts/Albedo/GrnGrass.dat
rtm/data/smarts/Albedo/GrnlSnow.dat
rtm/data/smarts/Albedo/LiteClay.dat
rtm/data/smarts/Albedo/LiteLoam.dat
rtm/data/smarts/Albedo/LiteSand.dat
rtm/data/smarts/Albedo/LiteSoil.dat
rtm/data/smarts/Albedo/LngGrass.dat
rtm/data/smarts/Albedo/LwnGrass.dat
rtm/data/smarts/Albedo/MEADOW1.DAT
rtm/data/smarts/Albedo/MEADOW2.DAT
rtm/data/smarts/Albedo/MeltSnow.dat
rtm/data/smarts/Albedo/NEVE.DAT
rtm/data/smarts/Albedo/OSeaWatr.dat
rtm/data/smarts/Albedo/OakTree.dat
rtm/data/smarts/Albedo/PINETREE.DAT
rtm/data/smarts/Albedo/PaleLoam.dat
