Metadata-Version: 1.0
Name: RTM
Version: 0.2.6
Summary: Numerical Computations for Radiative Transfer Modelling
Home-page: UNKNOWN
Author: Philip Schleihauf
Author-email: uniphil@gmail.com
License: license.txt
Platform: UNKNOWN
